chatterpy_mistral/__init__.py
chatterpy_mistral/__main__.py
chatterpy_mistral/banter.py
chatterpy_mistral/compliments.py
chatterpy_mistral/funfacts.py
chatterpy_mistral/pickuplines.py
chatterpy_mistral/smalltalk.py
chatterpy_mistral-0.0.9.dist-info/licenses/LICENSE
chatterpy_mistral-0.0.9.dist-info/METADATA
chatterpy_mistral-0.0.9.dist-info/WHEEL
chatterpy_mistral-0.0.9.dist-info/entry_points.txt
chatterpy_mistral-0.0.9.dist-info/top_level.txt
chatterpy_mistral-0.0.9.dist-info/RECORD
