Metadata-Version: 2.4
Name: chatterpy_mistral
Version: 0.0.9
Summary: Lighthearted conversation helpers (fun facts, etc.)
Author-email: Mahabub Alif <ma7205@nyu.edu>, Sydney Nadeau <sen5217@nyu.edu>, Susan Wang <sw5556@nyu.edu>, Aden Juda <asj8335@nyu.edu>, Serena Wang <sw5695@nyu.edu>
License:                     GNU GENERAL PUBLIC LICENSE
Project-URL: Homepage, https://github.com/swe-students-fall2025/3-python-package-team_mistral
Project-URL: Issues, https://github.com/swe-students-fall2025/3-python-package-team_mistral.git
Keywords: python,package,build,tutorial
Classifier: Programming Language :: Python :: 3
Classifier: Intended Audience :: Education
Classifier: License :: OSI Approved :: GNU General Public License v3 (GPLv3)
Classifier: Operating System :: OS Independent
Requires-Python: >=3.9
License-File: LICENSE
Provides-Extra: dev
Requires-Dist: pytest; extra == "dev"
Dynamic: license-file
